{"cameraMode":{"drawMode":0,"name":"Shaded","section":"Shading Mode"},"sceneLighting":true,"audioPlay":false,"sceneViewState":{"m_AlwaysRefresh":false,"showFog":true,"showSkybox":true,"showFlares":true,"showImageEffects":true,"showParticleSystems":true,"showVisualEffectGraphs":true,"m_FxEnabled":true},"in2DMode":false,"pivot":{"x":-0.41289547085762026,"y":4.574556350708008,"z":-4.770088195800781},"rotation":{"x":0.10432881116867066,"y":0.6726951003074646,"z":-0.09553489089012146,"w":0.7265364527702332},"size":2.4648513793945314,"orthographic":false}